{"Practical":{"Practical":{"currentFile":{"count":1,"lastUpdated":1758990089656}}},"anomaly":{"anomaly":{"currentFile":{"count":1,"lastUpdated":1759162045358}}},"transformers":{"transformers":{"currentFile":{"count":1,"lastUpdated":1759162199875}}},"original":{"original":{"currentFile":{"count":1,"lastUpdated":1759162502075}}},"right":{"right":{"currentFile":{"count":1,"lastUpdated":1759162652634}}},"Transformers":{"Transformers":{"currentFile":{"count":1,"lastUpdated":1759168017084}}},"technologies":{"technologies":{"currentFile":{"count":1,"lastUpdated":1759168074773}}},"lightweight":{"lightweight":{"currentFile":{"count":3,"lastUpdated":1759169603224}}},"BARTPredict":{"BARTPredict":{"currentFile":{"count":5,"lastUpdated":1760463008068}}},"additional":{"additional":{"currentFile":{"count":1,"lastUpdated":1759169625848}}},"component":{"component":{"currentFile":{"count":1,"lastUpdated":1759169627504}}},"Already":{"Already":{"currentFile":{"count":1,"lastUpdated":1759170756611}}},"full-fledged":{"full-fledged":{"currentFile":{"count":1,"lastUpdated":1759424191381}}},"interaest":{"interaest":{"currentFile":{"count":1,"lastUpdated":1759909186721}}},"detector":{"detector":{"currentFile":{"count":1,"lastUpdated":1759994182611}}},"predict":{"predict":{"currentFile":{"count":1,"lastUpdated":1759994299332}}},"header":{"header":{"currentFile":{"count":1,"lastUpdated":1759994320994}}},"field":{"field":{"currentFile":{"count":1,"lastUpdated":1759994323041}}},"mixture":{"mixture":{"currentFile":{"count":1,"lastUpdated":1759994404116}}},"research":{"research":{"currentFile":{"count":1,"lastUpdated":1759994960889}}},"packet":{"packet":{"currentFile":{"count":1,"lastUpdated":1759995365804}}},"completely":{"completely":{"currentFile":{"count":1,"lastUpdated":1759995740419}}},"classifier":{"classifier":{"currentFile":{"count":1,"lastUpdated":1759995835368}}},"probability":{"probability":{"currentFile":{"count":3,"lastUpdated":1760286801177}}},"malicious":{"malicious":{"currentFile":{"count":2,"lastUpdated":1760285713107}}},"initial":{"initial":{"currentFile":{"count":1,"lastUpdated":1760026865496}}},"would":{"would":{"currentFile":{"count":2,"lastUpdated":1760376497387}}},"session":{"session":{"currentFile":{"count":3,"lastUpdated":1760286803832}}},"current":{"current":{"currentFile":{"count":1,"lastUpdated":1760286703630}}},"attack":{"attack":{"currentFile":{"count":1,"lastUpdated":1760286729504}}},"Benign":{"Benign":{"currentFile":{"count":1,"lastUpdated":1760286921496}}},"Spoofing":{"Spoofing":{"currentFile":{"count":1,"lastUpdated":1760287217751}}},"message":{"message":{"currentFile":{"count":1,"lastUpdated":1760455668232}}},"Multiple":{"Multiple":{"currentFile":{"count":1,"lastUpdated":1760455860722}}},"access":{"access":{"currentFile":{"count":1,"lastUpdated":1760461304718}}},"context":{"context":{"currentFile":{"count":1,"lastUpdated":1760461365931}}},"never-before":{"never-before":{"currentFile":{"count":1,"lastUpdated":1760462462895}}},"logically":{"logically":{"currentFile":{"count":1,"lastUpdated":1760462556146}}},"packets":{"packets":{"currentFile":{"count":1,"lastUpdated":1760462694013}}},"replicate":{"replicate":{"currentFile":{"count":1,"lastUpdated":1760462810150}}},"network":{"network":{"currentFile":{"count":1,"lastUpdated":1760463513628}}},"considerations":{"considerations":{"currentFile":{"count":1,"lastUpdated":1760463763088}}},"protocols":{"protocols":{"currentFile":{"count":2,"lastUpdated":1760560148919}}},"model":{"model":{"currentFile":{"count":2,"lastUpdated":1760603681699}}},"Encapsulation":{"Encapsulation":{"currentFile":{"count":1,"lastUpdated":1760559072329}}},"encapsulation":{"encapsulation":{"currentFile":{"count":1,"lastUpdated":1760559094594}}},"restrictions":{"restrictions":{"currentFile":{"count":2,"lastUpdated":1760569101408}}},"application":{"application":{"currentFile":{"count":2,"lastUpdated":1760603876742}}},"address":{"address":{"currentFile":{"count":1,"lastUpdated":1760566252650}}},"architecture":{"architecture":{"currentFile":{"count":1,"lastUpdated":1760566610620}}},"alternative":{"alternative":{"currentFile":{"count":3,"lastUpdated":1760613763955}}},"precisely":{"precisely":{"currentFile":{"count":1,"lastUpdated":1760569411690}}},"potential":{"potential":{"currentFile":{"count":1,"lastUpdated":1760602473629}}},"broader":{"broader":{"currentFile":{"count":1,"lastUpdated":1760603872255}}},"Predicting an attack":{"Predicting an attack":{"internalLink":{"count":1,"lastUpdated":1760613536586}}}}